{
  "entry_id": "VIDEO_GARY_CHAPMAN_QQ_eb5r0dxM",
  "topic": [
    "Marriage"
  ],
  "sub_topic": null,
  "faith_perspective": "Christian",
  "source_type": "Video Resource",
  "source_reference": {
    "text": "Loving Your Spouse When You Feel Like Walking\u2026 by Gary ... (Video by Gary Chapman)",
    "url": "https://www.youtube.com/watch?v=QQ_eb5r0dxM"
  },
  "content_summary": "... on you and your spouse An experienced marriage and family counselor, Gary Chapman speaks to those whose spouse is any of the following ...",
  "content_detailed": "",
  "keywords": [
    "gary_chapman",
    "marriage"
  ],
  "related_scripture": [],
  "related_entries": [],
  "qa_pairs": [],
  "instruction_response": [],
  "metadata": {
    "creation_date": "2025-05-02",
    "last_modified_date": "2025-05-02",
    "contributor": "Manus_Agent_Data_Collection",
    "version": 1,
    "moderation_status": "Pending"
  }
}